{
  "db_name": "MySQL",
  "query": "SELECT COUNT(*) FROM login_attempts WHERE\n\t\t  username = ?\n\t\t  AND ip_address = ?\n\t\t  AND time > ?",
  "describe": {
    "columns": [
      {
        "ordinal": 0,
        "name": "COUNT(*)",
        "type_info": {
          "type": "LongLong",
          "flags": "NOT_NULL | BINARY",
          "char_set": 63,
          "max_size": 21
        }
      }
    ],
    "parameters": {
      "Right": 3
    },
    "nullable": [
      false
    ]
  },
  "hash": "209ddbd47d0fdf6b41ed0cc1e6ae614a27513a61d3c246ea411b9263a3f1eb73"
}
